azure/mgmt/neonpostgres/__init__.py
azure/mgmt/neonpostgres/_client.py
azure/mgmt/neonpostgres/_configuration.py
azure/mgmt/neonpostgres/_model_base.py
azure/mgmt/neonpostgres/_patch.py
azure/mgmt/neonpostgres/_serialization.py
azure/mgmt/neonpostgres/_validation.py
azure/mgmt/neonpostgres/_version.py
azure/mgmt/neonpostgres/py.typed
azure/mgmt/neonpostgres/aio/__init__.py
azure/mgmt/neonpostgres/aio/_client.py
azure/mgmt/neonpostgres/aio/_configuration.py
azure/mgmt/neonpostgres/aio/_patch.py
azure/mgmt/neonpostgres/aio/operations/__init__.py
azure/mgmt/neonpostgres/aio/operations/_operations.py
azure/mgmt/neonpostgres/aio/operations/_patch.py
azure/mgmt/neonpostgres/models/__init__.py
azure/mgmt/neonpostgres/models/_enums.py
azure/mgmt/neonpostgres/models/_models.py
azure/mgmt/neonpostgres/models/_patch.py
azure/mgmt/neonpostgres/operations/__init__.py
azure/mgmt/neonpostgres/operations/_operations.py
azure/mgmt/neonpostgres/operations/_patch.py
azure_mgmt_neonpostgres-1.0.0.dist-info/LICENSE
azure_mgmt_neonpostgres-1.0.0.dist-info/METADATA
azure_mgmt_neonpostgres-1.0.0.dist-info/WHEEL
azure_mgmt_neonpostgres-1.0.0.dist-info/top_level.txt
azure_mgmt_neonpostgres-1.0.0.dist-info/RECORD
